[{"start": 0.0, "end": 7.3999996, "text": "...de fotografías, de... no sé, de... cosas como eso, que necesitan mucha inteligencia.", "speaker": null}, {"start": 8.62, "end": 11.099999, "text": "Yo no tengo más que ver este número.", "speaker": null}, {"start": 13.44, "end": 16.06, "text": "A mí me parece que es el que está más grande que yo.", "speaker": null}, {"start": 17.0, "end": 20.42, "text": "Yo a mí me parece que es el que tiene un número muy, muy, muy grande.", "speaker": null}, {"start": 21.56, "end": 23.0, "text": "Uno, dos...", "speaker": null}, {"start": 23.619999, "end": 28.0, "text": "Yo creo que muchísimos, no sé, cuatro, cinco, seis, siete, ocho, siete...", "speaker": null}, {"start": 30.0, "end": 31.0, "text": "con mis actividades", "speaker": null}, {"start": 31.0, "end": 34.86, "text": "y hago muchísimas", "speaker": null}, {"start": 34.86, "end": 36.079998, "text": "actividades industriales", "speaker": null}, {"start": 36.079998, "end": 38.46, "text": "yo hago", "speaker": null}, {"start": 38.46, "end": 39.5, "text": "como toda la gente", "speaker": null}, {"start": 39.5, "end": 41.66, "text": "yo hago muchas actividades", "speaker": null}, {"start": 41.66, "end": 42.84, "text": "con nuestros amigos", "speaker": null}, {"start": 42.84, "end": 46.3, "text": "pues voy a las plantas", "speaker": null}, {"start": 46.3, "end": 47.7, "text": "yo sigo en los espacios", "speaker": null}, {"start": 47.7, "end": 49.3, "text": "yo sigo en los almacenes", "speaker": null}, {"start": 49.3, "end": 50.1, "text": "yo sigo", "speaker": null}, {"start": 50.1, "end": 51.3, "text": "en lo que me gusta", "speaker": null}, {"start": 51.3, "end": 54.64, "text": "incluso a los partos industriales", "speaker": null}, {"start": 54.64, "end": 55.579998, "text": "los estamos haciendo", "speaker": null}, {"start": 55.579998, "end": 57.72, "text": "y quiero que vean", "speaker": null}, {"start": 57.72, "end": 58.579998, "text": "esa gran actividad", "speaker": null}, {"start": 58.579998, "end": 64.84, "text": "Entonces, el gobierno de los hijos, yo digo, chica, la verdad es que un peso es caro.", "speaker": null}, {"start": 65.84, "end": 70.28, "text": "Y lo que se sino a la gente, el robo, que llegan a un cliente de un grupo,", "speaker": null}, {"start": 71.2, "end": 74.34, "text": "va a un impuesto de la gente, y en cambio, ¿cuál es?", "speaker": null}, {"start": 74.52, "end": 75.56, "text": "¿No tienen tanta ropa?", "speaker": null}, {"start": 76.32, "end": 76.96, "text": "La mitad.", "speaker": null}, {"start": 77.439995, "end": 78.42, "text": "Sí, exacto.", "speaker": null}, {"start": 79.5, "end": 83.6, "text": "Y aparte, la gente no está con la gente, no está con la gente,", "speaker": null}, {"start": 83.6, "end": 86.46, "text": "no tienen el derecho a la relación que hay con las familias.", "speaker": null}, {"start": 86.46, "end": 92.02, "text": "y luego yo soy un gran", "speaker": null}, {"start": 92.02, "end": 93.18, "text": "entonces sería un gran", "speaker": null}, {"start": 93.18, "end": 96.479996, "text": "y ya todos son lugares", "speaker": null}, {"start": 96.479996, "end": 97.14, "text": "de confianza", "speaker": null}, {"start": 97.14, "end": 97.74, "text": "yo digo", "speaker": null}, {"start": 97.74, "end": 100.42, "text": "que no debería ser un lugar de confianza", "speaker": null}, {"start": 100.42, "end": 103.04, "text": "yo por ejemplo vivo en las fábricas", "speaker": null}, {"start": 103.04, "end": 103.979996, "text": "que hay cualquiera", "speaker": null}, {"start": 103.979996, "end": 106.9, "text": "y la forma en que vivo", "speaker": null}, {"start": 106.9, "end": 108.34, "text": "es con mis cosas", "speaker": null}, {"start": 108.34, "end": 110.26, "text": "yo no tengo que vivir con eso", "speaker": null}, {"start": 110.26, "end": 112.159996, "text": "dejo mis cosas", "speaker": null}, {"start": 112.159996, "end": 115.54, "text": "los planos, la maquinaria", "speaker": null}, {"start": 115.54, "end": 116.54, "text": "Gracias.", "speaker": null}, {"start": 145.54, "end": 147.87999, "text": "¿Qué pasa con las empresas? ¿Qué pasa con eso?", "speaker": null}, {"start": 149.01999, "end": 151.45999, "text": "¿Qué pasa con la empresa? ¿Qué pasa con la empresa?", "speaker": null}, {"start": 151.45999, "end": 151.95999, "text": "¿Qué pasa con la empresa?", "speaker": null}, {"start": 157.01999, "end": 159.12, "text": "Pero bueno, depende de la empresa.", "speaker": null}, {"start": 159.28, "end": 159.78, "text": "¿Sí es así?", "speaker": null}, {"start": 161.7, "end": 163.73999, "text": "¿El que sí no cree que podría cambiar?", "speaker": null}, {"start": 164.54, "end": 166.45999, "text": "No, pues, sí.", "speaker": null}, {"start": 166.81999, "end": 171.29999, "text": "Es decir, que porque hay unos que son más, igual de Motorola, pero más altos.", "speaker": null}, {"start": 171.64, "end": 174.28, "text": "Pero, pues, si justo no tienen nada.", "speaker": null}, {"start": 175.54, "end": 182.54, "text": "el nuevo", "speaker": null}, {"start": 205.54, "end": 208.54, "text": "y ni siquiera pensamos para eso.", "speaker": null}, {"start": 208.54, "end": 215.54, "text": "Yo no sé que ya tienen la capacidad para bajar rapidísimo la información,", "speaker": null}, {"start": 215.54, "end": 222.018, "text": "instalarla rapid que coja rapid el coreano Para que los pueblos por ejemplo por ejemplo yo tengo un pueblo que juega mucho en el intercambio con tabones", "speaker": null}, {"start": 250.018, "end": 254.018, "text": "pero con eso juega, con eso juega.", "speaker": null}, {"start": 254.018, "end": 258.018, "text": "¿Con qué? ¿Esto se trata de un charly?", "speaker": null}, {"start": 258.018, "end": 262.018, "text": "Sí, sí. Es que", "speaker": null}, {"start": 262.018, "end": 266.018, "text": "es bien difícil con los Android, porque es que incluso dentro de la misma", "speaker": null}, {"start": 266.018, "end": 270.018, "text": "compañía, puede que uno esté bueno y el otro mal. O sea, por eso", "speaker": null}, {"start": 270.018, "end": 274.018, "text": "es muy fácil los iPhones, que todos salen bien. Pero", "speaker": null}, {"start": 274.018, "end": 278.018, "text": "esto no se sabe hasta", "speaker": null}, {"start": 278.018, "end": 280.638, "text": "hasta que empiezan a llegar a las tiendas de reparación", "speaker": null}, {"start": 280.638, "end": 283.078, "text": "no, pues estos fallan un rango aquí, estos fallan un rango acá", "speaker": null}, {"start": 283.078, "end": 284.71802, "text": "pero en general", "speaker": null}, {"start": 284.71802, "end": 289.358, "text": "o sea, si va a estar mucho más rápido que eso", "speaker": null}, {"start": 289.358, "end": 290.738, "text": "esto de", "speaker": null}, {"start": 290.738, "end": 292.038, "text": "el caso", "speaker": null}, {"start": 292.038, "end": 293.898, "text": "mínimo no me acuerdo", "speaker": null}, {"start": 293.898, "end": 295.99802, "text": "nunca me ha hablado de nada", "speaker": null}, {"start": 295.99802, "end": 298.478, "text": "ahora lo que si se hace", "speaker": null}, {"start": 298.478, "end": 299.678, "text": "es que se atarán", "speaker": null}, {"start": 299.678, "end": 300.998, "text": "ya estamos a lugar", "speaker": null}, {"start": 300.998, "end": 303.418, "text": "pero", "speaker": null}, {"start": 303.418, "end": 305.798, "text": "lo que hago es", "speaker": null}, {"start": 305.798, "end": 307.998, "text": "reiniciarlo y otra vez", "speaker": null}, {"start": 307.998, "end": 311.838, "text": "¿Cómo que de línea para su línea de negocio?", "speaker": null}, {"start": 312.758, "end": 313.778, "text": "Y ya vuelve a funcionar", "speaker": null}, {"start": 313.778, "end": 316.098, "text": "Pero es muy difícil", "speaker": null}, {"start": 316.098, "end": 317.198, "text": "¿Y el ofrecer un ofrecer?", "speaker": null}, {"start": 318.638, "end": 319.818, "text": "No, no creo que tenga", "speaker": null}, {"start": 319.818, "end": 320.758, "text": "Un problema", "speaker": null}, {"start": 320.758, "end": 322.758, "text": "Así de que le pueda recomendar", "speaker": null}, {"start": 322.758, "end": 324.358, "text": "Que le pueda recomendar una Amazon iPhone", "speaker": null}, {"start": 324.358, "end": 325.478, "text": "Pero", "speaker": null}, {"start": 325.478, "end": 329.138, "text": "Sí, justo con personas que ya están", "speaker": null}, {"start": 329.138, "end": 330.478, "text": "Acostumbradas de que siempre han usado", "speaker": null}, {"start": 330.478, "end": 332.518, "text": "O controlado la información", "speaker": null}, {"start": 332.518, "end": 334.958, "text": "A veces se intenta cambiar", "speaker": null}, {"start": 334.958, "end": 335.858, "text": "Y es más", "speaker": null}, {"start": 335.858, "end": 338.358, "text": "porque el sistema es un poco diferente de la interfaz", "speaker": null}, {"start": 338.358, "end": 341.298, "text": "entonces si es mejor así como", "speaker": null}, {"start": 341.298, "end": 342.65802, "text": "que es más rápido", "speaker": null}, {"start": 342.65802, "end": 343.958, "text": "que no se atora y así", "speaker": null}, {"start": 343.958, "end": 346.398, "text": "pero que ya es más constante", "speaker": null}, {"start": 346.398, "end": 348.178, "text": "que no estén acostumbrados", "speaker": null}, {"start": 348.178, "end": 350.05798, "text": "a la interfaz", "speaker": null}, {"start": 350.05798, "end": 351.278, "text": "que la cancela", "speaker": null}, {"start": 351.278, "end": 353.378, "text": "una música que le llaman a la teléfono", "speaker": null}, {"start": 353.378, "end": 354.818, "text": "que se muere", "speaker": null}, {"start": 354.818, "end": 355.758, "text": "me ha pasado que", "speaker": null}, {"start": 355.758, "end": 357.298, "text": "le digo que me fui a estudiar", "speaker": null}, {"start": 357.298, "end": 360.078, "text": "algunas veces que dejaba mi teléfono en las puertas", "speaker": null}, {"start": 360.078, "end": 362.258, "text": "o sea que me voy y llamo a un grupo", "speaker": null}, {"start": 362.258, "end": 363.258, "text": "y tengo una comisión", "speaker": null}, {"start": 363.258, "end": 364.958, "text": "un disfraz de disparado", "speaker": null}, {"start": 364.958, "end": 367.678, "text": "y yo crezco de gente", "speaker": null}, {"start": 367.678, "end": 371.798, "text": "y a veces lo que se lleva a la vida", "speaker": null}, {"start": 371.798, "end": 374.258, "text": "para no le mientan", "speaker": null}, {"start": 374.258, "end": 376.318, "text": "que a veces no es el trabajo", "speaker": null}, {"start": 376.318, "end": 378.41803, "text": "no es el trabajo", "speaker": null}, {"start": 378.41803, "end": 380.03802, "text": "entonces", "speaker": null}, {"start": 380.03802, "end": 382.078, "text": "no estoy muy acostumbrado", "speaker": null}, {"start": 382.078, "end": 384.118, "text": "a esa configuración", "speaker": null}, {"start": 384.118, "end": 387.018, "text": "por eso me gusta", "speaker": null}, {"start": 387.018, "end": 388.818, "text": "y todo se aprende", "speaker": null}, {"start": 388.818, "end": 389.638, "text": "todo", "speaker": null}, {"start": 389.638, "end": 394.258, "text": "pero yo si estoy en ese proceso", "speaker": null}, {"start": 394.258, "end": 396.518, "text": "en el interior", "speaker": null}, {"start": 396.518, "end": 397.918, "text": "ni siquiera lo he destapado", "speaker": null}, {"start": 397.918, "end": 399.538, "text": "en ya dos semanas", "speaker": null}, {"start": 399.538, "end": 401.638, "text": "no lo he destapado", "speaker": null}, {"start": 401.638, "end": 404.918, "text": "pero esa fue una mala decisión de mi parte", "speaker": null}, {"start": 404.918, "end": 405.878, "text": "la pregunta es", "speaker": null}, {"start": 405.878, "end": 407.418, "text": "¿no estuvo tan mal?", "speaker": null}, {"start": 408.21802, "end": 410.038, "text": "no, no, tenemos", "speaker": null}, {"start": 410.038, "end": 413.078, "text": "problemas", "speaker": null}, {"start": 413.078, "end": 418.578, "text": "que tienen chingos de modelos", "speaker": null}, {"start": 418.578, "end": 419.17798, "text": "así que van", "speaker": null}, {"start": 419.17798, "end": 421.79797, "text": "casi cada año sacan como 10, 15 modelos", "speaker": null}, {"start": 421.79797, "end": 423.958, "text": "no son difíciles", "speaker": null}, {"start": 423.958, "end": 426.198, "text": "compararlos con otros, con muchísimos.", "speaker": null}, {"start": 427.338, "end": 427.638, "text": "Pero,", "speaker": null}, {"start": 428.21802, "end": 428.898, "text": "yo, en general.", "speaker": null}, {"start": 429.47803, "end": 430.958, "text": "La muchacha me ofreció", "speaker": null}, {"start": 430.958, "end": 433.238, "text": "como 1.800, como 1.000.", "speaker": null}, {"start": 433.97803, "end": 435.078, "text": "Como 1.000, sí.", "speaker": null}, {"start": 436.178, "end": 437.778, "text": "Pero me dijo que era lo mismo.", "speaker": null}, {"start": 438.258, "end": 440.03802, "text": "Me dijo, realmente, lo que cambia es la cámara,", "speaker": null}, {"start": 440.238, "end": 441.178, "text": "lo que cambia es", "speaker": null}, {"start": 441.178, "end": 442.698, "text": "algunos aditamentos.", "speaker": null}, {"start": 443.298, "end": 455.036, "text": "Lo que m me gustar mejorar fue el procesador Pero pues el que pone un procesador y viene ya con m otras cosas o sea que pues igual si no ocupa pues me alcanza pero", "speaker": null}, {"start": 456.556, "end": 465.036, "text": "es que también a veces los que tienen mejor procesador son peores en...", "speaker": null}, {"start": 465.756, "end": 469.036, "text": "en que se rompan los ojos, porque como traen...", "speaker": null}, {"start": 469.036, "end": 471.036, "text": "o estos que nos...", "speaker": null}, {"start": 471.036, "end": 482.316, "text": "si se le rompe la pantalla igual más allá la pantalla vale 50% de la puerta", "speaker": null}, {"start": 482.316, "end": 484.556, "text": "y son más delicadas", "speaker": null}, {"start": 484.556, "end": 488.13602, "text": "entonces esas casi no", "speaker": null}, {"start": 488.13602, "end": 491.116, "text": "porque al principio la luchada estaba pegada", "speaker": null}, {"start": 491.116, "end": 492.776, "text": "queríamos meter un cubo", "speaker": null}, {"start": 492.776, "end": 497.196, "text": "si es lo malo", "speaker": null}, {"start": 497.196, "end": 498.85602, "text": "pero si hay una luchada", "speaker": null}, {"start": 498.85602, "end": 501.73602, "text": "es que este sí es bastante delicado", "speaker": null}, {"start": 501.73602, "end": 503.936, "text": "dice que no hay ahorita", "speaker": null}, {"start": 503.936, "end": 505.29602, "text": "ni siquiera reflexiones", "speaker": null}, {"start": 505.29602, "end": 508.23602, "text": "no hay ni siquiera reflexiones", "speaker": null}, {"start": 508.23602, "end": 516.116, "text": "yo fui preguntando", "speaker": null}, {"start": 516.116, "end": 517.81604, "text": "y llegué a la conclusión", "speaker": null}, {"start": 517.81604, "end": 520.196, "text": "es porque es el que me gustaba", "speaker": null}, {"start": 520.196, "end": 520.776, "text": "en la media", "speaker": null}, {"start": 520.776, "end": 523.356, "text": "muy jodido", "speaker": null}, {"start": 523.356, "end": 525.156, "text": "y muy delicado", "speaker": null}, {"start": 525.156, "end": 526.716, "text": "y lo que me preocupó", "speaker": null}, {"start": 526.716, "end": 528.536, "text": "es que no se me cae con esa idea", "speaker": null}, {"start": 528.536, "end": 530.956, "text": "o de oro, o algo,", "speaker": null}, {"start": 531.076, "end": 532.956, "text": "yo no tengo interés en las empresas,", "speaker": null}, {"start": 533.676, "end": 534.956, "text": "porque no iba a estar, ayer nada,", "speaker": null}, {"start": 535.156, "end": 537.196, "text": "me gustó, ayer me agarró un tormento,", "speaker": null}, {"start": 537.856, "end": 538.756, "text": "pero tormento,", "speaker": null}, {"start": 539.596, "end": 540.776, "text": "todo lo que hice fue que me metí", "speaker": null}, {"start": 540.776, "end": 541.696, "text": "en el barrio,", "speaker": null}, {"start": 541.856, "end": 547.556, "text": "y si se me gotean,", "speaker": null}, {"start": 548.81604, "end": 549.616, "text": "y me meten,", "speaker": null}, {"start": 550.216, "end": 553.43604, "text": "y yo vuelvo a ir de mis hijas,", "speaker": null}, {"start": 553.43604, "end": 557.716, "text": "y aparte que es muy diferente", "speaker": null}, {"start": 557.716, "end": 558.256, "text": "la actividad,", "speaker": null}, {"start": 558.536, "end": 560.516, "text": "muy bien", "speaker": null}, {"start": 560.516, "end": 563.916, "text": "yo lo veía", "speaker": null}, {"start": 563.916, "end": 565.296, "text": "cuando mi hija", "speaker": null}, {"start": 565.296, "end": 566.556, "text": "que es médica", "speaker": null}, {"start": 566.556, "end": 568.656, "text": "ella es bastante", "speaker": null}, {"start": 568.656, "end": 570.276, "text": "en los estudios", "speaker": null}, {"start": 570.276, "end": 572.376, "text": "entonces", "speaker": null}, {"start": 572.376, "end": 574.43604, "text": "tiene mucha habilidad", "speaker": null}, {"start": 574.43604, "end": 576.676, "text": "ya puede abrir", "speaker": null}, {"start": 576.676, "end": 577.916, "text": "un estudio", "speaker": null}, {"start": 577.916, "end": 579.856, "text": "una tomografía", "speaker": null}, {"start": 579.856, "end": 582.016, "text": "del cerebro", "speaker": null}, {"start": 582.016, "end": 584.416, "text": "y se ve perfectamente", "speaker": null}, {"start": 584.416, "end": 587.856, "text": "cosas como eso", "speaker": null}, {"start": 587.856, "end": 589.736, "text": "Pero yo no, no, no, no, no.", "speaker": null}, {"start": 591.176, "end": 595.696, "text": "Lo más que puede pasar es que se da más negro que en otro teléfono.", "speaker": null}, {"start": 597.43604, "end": 598.656, "text": "Porque lo hice de ahí.", "speaker": null}, {"start": 598.656, "end": 599.496, "text": "¿Qué es lo que te pasa?", "speaker": null}, {"start": 601.336, "end": 604.956, "text": "Yo le tomo una imagen, un documento,", "speaker": null}, {"start": 605.716, "end": 607.976, "text": "y me digo, un hijo de cinco, seis hijos que me ha cambiado el número,", "speaker": null}, {"start": 608.236, "end": 610.256, "text": "que me había fallado la vista.", "speaker": null}, {"start": 611.356, "end": 613.11597, "text": "Y yo le digo, pues eso es básico, el chucho de hijo.", "speaker": null}, {"start": 613.576, "end": 614.276, "text": "¿Por qué le pasa?", "speaker": null}, {"start": 614.276, "end": 616.276, "text": "¿Puedo?", "speaker": null}, {"start": 616.276, "end": 616.836, "text": "¿Puedo?", "speaker": null}, {"start": 618.496, "end": 619.056, "text": "¿Ya?", "speaker": null}, {"start": 619.536, "end": 620.196, "text": "¿No es un cambio?", "speaker": null}, {"start": 620.61597, "end": 621.156, "text": "¿No es un cambio?", "speaker": null}, {"start": 621.156, "end": 622.716, "text": "¿Puedo hacer un servicio también?", "speaker": null}, {"start": 623.756, "end": 624.576, "text": "¿El chip?", "speaker": null}, {"start": 626.256, "end": 627.776, "text": "¿Entonces puedo meter este?", "speaker": null}, {"start": 627.916, "end": 630.036, "text": "Pues sí, yo lo que intenté", "speaker": null}, {"start": 630.036, "end": 632.536, "text": "incluso buscar en las configuraciones", "speaker": null}, {"start": 632.536, "end": 633.716, "text": "cómo apagar el 5G", "speaker": null}, {"start": 633.716, "end": 635.776, "text": "porque le va a dar más problema al telón", "speaker": null}, {"start": 635.776, "end": 637.636, "text": "de que beneficios.", "speaker": null}, {"start": 637.816, "end": 638.376, "text": "¿De beneficios?", "speaker": null}, {"start": 638.376, "end": 638.816, "text": "Ajá.", "speaker": null}, {"start": 641.61597, "end": 644.11597, "text": "Yo aquí le digo, la ventaja de esto", "speaker": null}, {"start": 644.116, "end": 648.356, "text": "es que cuando el 5G se generalice, ya no va a tener que cambiar.", "speaker": null}, {"start": 648.69604, "end": 650.636, "text": "Sí, pero lleva cinco años generalizando.", "speaker": null}, {"start": 652.636, "end": 653.276, "text": "¿Y la?", "speaker": null}, {"start": 653.616, "end": 653.856, "text": "La.", "speaker": null}, {"start": 654.336, "end": 654.776, "text": "Ah, la.", "speaker": null}, {"start": 655.616, "end": 656.056, "text": "Ok.", "speaker": null}, {"start": 656.93604, "end": 657.416, "text": "Salud, vale.", "speaker": null}, {"start": 657.776, "end": 658.676, "text": "Pues vamos al nuestro.", "speaker": null}, {"start": 659.956, "end": 660.716, "text": "A ver, ¿qué es?", "speaker": null}, {"start": 662.536, "end": 667.416, "text": "El día de hoy quedamos y vamos a ver lo relativo al sistema.", "speaker": null}, {"start": 667.416, "end": 669.416, "text": "Gracias.", "speaker": null}, {"start": 670.054, "end": 681.774, "text": "Aquí se van a encontrar infinidad de publicaciones que de alguna manera pueden variar.", "speaker": null}, {"start": 683.614, "end": 685.57404, "text": "Y las voy a llamar publicaciones.", "speaker": null}, {"start": 686.334, "end": 694.01404, "text": "No porque sean una publicación, sino porque en los lugares a los que ustedes tendrían que consultar no es su día.", "speaker": null}, {"start": 695.314, "end": 697.494, "text": "Esto les va a decir puras estupideces.", "speaker": null}, {"start": 697.494, "end": 701.314, "text": "y el video se lo puede ir demostrando.", "speaker": null}, {"start": 702.39404, "end": 703.434, "text": "Cuando menos para nosotros,", "speaker": null}, {"start": 703.594, "end": 705.174, "text": "tenemos un control de los servicios.", "speaker": null}, {"start": 709.45404, "end": 710.63403, "text": "Más de paro,", "speaker": null}, {"start": 711.254, "end": 713.914, "text": "tenemos que buscar alguna gente de consulta", "speaker": null}, {"start": 713.914, "end": 716.554, "text": "y lo más adecuado serían", "speaker": null}, {"start": 716.554, "end": 719.114, "text": "fuentes de consulta oficiales.", "speaker": null}, {"start": 720.19403, "end": 722.314, "text": "Y si ustedes se meten en una fuente de consulta oficial,", "speaker": null}, {"start": 722.314, "end": 722.854, "text": "por ejemplo,", "speaker": null}, {"start": 723.594, "end": 725.494, "text": "lo pueden hacer por ponerlo", "speaker": null}, {"start": 725.494, "end": 727.354, "text": "nada más en el pólizis", "speaker": null}, {"start": 727.354, "end": 730.914, "text": "en la página de la Secretaría de Hacienda", "speaker": null}, {"start": 730.914, "end": 733.834, "text": "que normalmente es a donde lo consultan", "speaker": null}, {"start": 733.834, "end": 736.254, "text": "lo pueden hacer en la página del Banco de México", "speaker": null}, {"start": 736.254, "end": 740.054, "text": "o en cualquiera de ellas que son fuentes oficiales", "speaker": null}, {"start": 740.054, "end": 742.374, "text": "y aún entre las mismas autoridades", "speaker": null}, {"start": 742.374, "end": 744.95404, "text": "que son fuentes oficiales", "speaker": null}, {"start": 744.95404, "end": 747.174, "text": "si tú comparas el organigrama del Banco de México", "speaker": null}, {"start": 747.174, "end": 748.934, "text": "con el organigrama de la Secretaría de Hacienda", "speaker": null}, {"start": 748.934, "end": 751.01404, "text": "que son las más fuertes, las más importantes", "speaker": null}, {"start": 751.01404, "end": 752.674, "text": "son diferentes", "speaker": null}, {"start": 752.674, "end": 755.374, "text": "porque se concentran a su", "speaker": null}, {"start": 755.374, "end": 758.39404, "text": "segmento", "speaker": null}, {"start": 758.39404, "end": 759.614, "text": "a su especialidad", "speaker": null}, {"start": 759.614, "end": 762.714, "text": "entonces no podíamos definir", "speaker": null}, {"start": 762.714, "end": 764.01404, "text": "con precisión", "speaker": null}, {"start": 764.01404, "end": 766.414, "text": "cuál es mejor que el otro", "speaker": null}, {"start": 766.414, "end": 767.994, "text": "yo te diría lo mejor sería", "speaker": null}, {"start": 767.994, "end": 769.614, "text": "integrarlos", "speaker": null}, {"start": 769.614, "end": 771.45404, "text": "y hacer uno solo", "speaker": null}, {"start": 771.45404, "end": 774.39404, "text": "pero te va a salir un chorizo tamaño", "speaker": null}, {"start": 774.39404, "end": 776.094, "text": "un caguato, esos son los que alivian", "speaker": null}, {"start": 776.094, "end": 777.19403, "text": "más inmensos", "speaker": null}, {"start": 777.19403, "end": 779.69403, "text": "la generalidad nos dice", "speaker": null}, {"start": 779.69403, "end": 780.69403, "text": "que para que", "speaker": null}, {"start": 780.69403, "end": 783.554, "text": "ahora, ¿por qué no estoy hablando de la alivian?", "speaker": null}, {"start": 783.554, "end": 787.674, "text": "porque comprender el sistema de medicina", "speaker": null}, {"start": 787.674, "end": 789.434, "text": "es mucho más fácil", "speaker": null}, {"start": 789.434, "end": 791.57404, "text": "es inmenso", "speaker": null}, {"start": 791.57404, "end": 793.914, "text": "es muchísima información", "speaker": null}, {"start": 793.914, "end": 796.034, "text": "para la clase de ustedes", "speaker": null}, {"start": 796.034, "end": 797.234, "text": "no es tan importante", "speaker": null}, {"start": 797.234, "end": 798.15405, "text": "para ustedes", "speaker": null}, {"start": 798.15405, "end": 800.494, "text": "por la naturaleza de su profesión", "speaker": null}, {"start": 800.494, "end": 802.354, "text": "pero para nosotros sí", "speaker": null}, {"start": 802.354, "end": 804.534, "text": "porque nosotros nos basamos", "speaker": null}, {"start": 804.534, "end": 806.934, "text": "sobre todo en", "speaker": null}, {"start": 806.934, "end": 808.214, "text": "autoridades", "speaker": null}, {"start": 808.214, "end": 809.77405, "text": "nosotros como contadores", "speaker": null}, {"start": 809.77405, "end": 812.27405, "text": "todo el tiempo tenemos que estar cumpliendo", "speaker": null}, {"start": 812.27405, "end": 816.114, "text": "con las normas de regulación que nos da cada autoridad.", "speaker": null}, {"start": 816.874, "end": 821.614, "text": "Ejemplo, entendemos como autoridad, no lo sé, repito, a la Secretaría de Hacienda y Crítico Público,", "speaker": null}, {"start": 821.974, "end": 826.814, "text": "es una autoridad infalible, no nada más para nosotros.", "speaker": null}, {"start": 827.934, "end": 830.714, "text": "O sea, nosotros la tenemos que aplicar para ustedes.", "speaker": null}, {"start": 831.714, "end": 834.614, "text": "¿Me explico? ¿Por qué? Porque pongamos una hipótesis.", "speaker": null}, {"start": 835.19403, "end": 836.454, "text": "Carlos tiene un negocio.", "speaker": null}, {"start": 837.874, "end": 841.334, "text": "Carlos dirá, bueno, yo tengo un negocio chico, mediano, grande, eso no nos interesa.", "speaker": null}, {"start": 841.334, "end": 844.314, "text": "pero Carlos desde el momento en que tiene un negocio", "speaker": null}, {"start": 844.314, "end": 846.374, "text": "está obligado a registrarse", "speaker": null}, {"start": 846.374, "end": 848.314, "text": "y está obligado", "speaker": null}, {"start": 848.314, "end": 850.614, "text": "a cumplir con las obligaciones", "speaker": null}, {"start": 850.614, "end": 851.534, "text": "tributarias", "speaker": null}, {"start": 851.534, "end": 854.39404, "text": "en pocas palabras a pagar impuestos", "speaker": null}, {"start": 854.39404, "end": 856.69403, "text": "entonces yo tengo que estar", "speaker": null}, {"start": 856.69403, "end": 858.974, "text": "enterado en que ramo", "speaker": null}, {"start": 858.974, "end": 860.89404, "text": "o en que mundo se mueve Carlos", "speaker": null}, {"start": 860.89404, "end": 862.654, "text": "para poder", "speaker": null}, {"start": 862.654, "end": 863.07404, "text": "que", "speaker": null}, {"start": 863.07404, "end": 866.494, "text": "llevar su negocio", "speaker": null}, {"start": 866.494, "end": 868.374, "text": "llevar su empresa dentro de", "speaker": null}, {"start": 868.374, "end": 870.614, "text": "la normatividad correcta", "speaker": null}, {"start": 870.614, "end": 876.614, "text": "No es lo mismo la normatividad que van a llevar ustedes, correcto, como informáticos,", "speaker": null}, {"start": 876.614, "end": 880.614, "text": "a la normatividad que va a llevar un médico o con el médico,", "speaker": null}, {"start": 880.614, "end": 888.614, "text": "o a la normatividad que va a llevar, no lo sé, a lo mejor una empresa de la industria metalmecánica,", "speaker": null}, {"start": 888.614, "end": 894.614, "text": "o a la normatividad que va a llevar una empresa con giro de alimentos.", "speaker": null}, {"start": 894.614, "end": 899.734, "text": "¿Se me explico? Se van a regir por distintas autoridades.", "speaker": null}]